rticonnextdds-connector/lib/linux-arm/libnddsc.so
rticonnextdds-connector/lib/linux-arm/libnddscore.so
rticonnextdds-connector/lib/linux-arm/librtiddsconnector.so
rticonnextdds-connector/lib/linux-arm64/libnddsc.so
rticonnextdds-connector/lib/linux-arm64/libnddscore.so
rticonnextdds-connector/lib/linux-arm64/librtiddsconnector.so
rticonnextdds-connector/lib/linux-x64/libnddsc.so
rticonnextdds-connector/lib/linux-x64/libnddscore.so
rticonnextdds-connector/lib/linux-x64/librtiddsconnector.so
rticonnextdds-connector/lib/osx-x64/libnddsc.dylib
rticonnextdds-connector/lib/osx-x64/libnddscore.dylib
rticonnextdds-connector/lib/osx-x64/librtiddsconnector.dylib
rticonnextdds-connector/lib/win-x64/nddsc.dll
rticonnextdds-connector/lib/win-x64/nddscore.dll
rticonnextdds-connector/lib/win-x64/rtiddsconnector.dll
rticonnextdds-connector/lib/win-x64/vcruntime140.dll
rticonnextdds_connector/__init__.py
rticonnextdds_connector/rticonnextdds_connector.py
rticonnextdds_connector-1.2.4.dist-info/LICENSE.pdf
rticonnextdds_connector-1.2.4.dist-info/METADATA
rticonnextdds_connector-1.2.4.dist-info/WHEEL
rticonnextdds_connector-1.2.4.dist-info/top_level.txt
rticonnextdds_connector-1.2.4.dist-info/RECORD
