Metadata-Version: 2.1
Name: rticonnextdds-connector
Version: 1.2.4
Summary: RTI Connector for Python
Home-page: https://github.com/rticommunity/rticonnextdds-connector-py
Author: RTI
Author-email: support@rti.com
License: RTI
Keywords: rti dds connext connector pub sub pub-sub iot
Platform: UNKNOWN
Classifier: Development Status :: 5 - Production/Stable
Classifier: Intended Audience :: Developers
Classifier: Topic :: System :: Distributed Computing
Classifier: License :: Other/Proprietary License
Classifier: Programming Language :: Python :: 2
Classifier: Programming Language :: Python :: 2.6
Classifier: Programming Language :: Python :: 2.7
Classifier: Programming Language :: Python :: 3
